Workbook

Sheet sales
A1: Invoice ID | B1: Branch | C1: City | D1: Customer type | E1: Gender | F1: Product line | G1: Unit price | H1: Quantity | I1: Tax 5% | J1: Total | K1: cogs | L1: Date | M1: Time | N1: Payment | O1: Rating | P1: =SUM(J2:J5,K2:K4) | Q1: =PRODUCT(G2:H2,H3:H6) | R1: =MAX(I2:I13) | S1: =MIN(H2:H12) | T1: =AVERAGE(G2:G8,I2:I8) | U1: =COUNT(F2:F4,G2:G6) | V1: =COUNTA(G2:G5,F2:F3) | W1: =ROUNDUP(O2,0) | X1: =ROUNDDOWN(O2,0) | Y1: =ROUND(O2,2) | Z1: =POWER(X2,2) | AA1: =SQRT(Z2) | AB1: =LEN(Y2) | AC1: =SUBTOTAL(2,W2:Y2)
A2: 750-67-8428 | B2: A | C2: Trichy | D2: Member | E2: Female | F2: Health and beauty | G2: 74.69 | H2: 7 | I2: 26.1415 | J2: 548.9715 | K2: 522.83 | L2: 43586 | M2: 0.54722222 | N2: Ewallet | O2: 9.1373232 | P2: =SUM(J2:J5,K2:K4) -> 2382.305 | Q2: =PRODUCT(G2:H2,H3:H6) -> 1024746.8 | R2: =MAX(I2:I13) -> 36.78 | S2: =MIN(H2:H12) -> 2 | T2: =AVERAGE(G2:G8,I2:I8) -> 41.805143 | U2: =COUNT(F2:F4,G2:G6) -> 5 | V2: =COUNTA(G2:G5,F2:F3) -> 6 | W2: =ROUNDUP(O2,0) -> 10 | X2: =ROUNDDOWN(O2,0) -> 9 | Y2: =ROUND(O2,2) -> 9.14 | Z2: =POWER(X2,2) -> 81 | AA2: =SQRT(Z2) -> 9 | AB2: =LEN(Y2) -> 4 | AC2: =SUBTOTAL(2,W2:Y2) -> 3
A3: 226-31-3081 | B3: C | C3: Chennai | D3: Normal | E3: Female | F3: Electronic accessories | G3: 15.28 | H3: 5 | I3: 3.82 | J3: 80.22 | K3: 76.4 | L3: 43680 | M3: 0.43680556 | N3: Cash | O3: 9.6 | W3: =ROUNDUP(R2,0) -> 37 | X3: =ROUNDDOWN(R2,0) -> 36 | Y3: =ROUND(R2,1) -> 36.8
A4: 631-41-3108 | B4: A | C4: Trichy | D4: Normal | E4: Male | F4: Home and lifestyle | G4: 46.33 | H4: 7 | I4: 16.2155 | J4: 340.5255 | K4: 324.31 | L4: 43527 | M4: 0.55763889 | N4: Credit card | O4: 7.4 | V4: 1000.4343 | W4: =ROUNDDOWN(V4,0) -> 1000
A5: 123-19-1176 | B5: A | C5: Trichy | D5: Member | E5: Male | F5: Health and beauty | G5: 58.22 | H5: 8 | I5: 23.288 | J5: 489.048 | K5: 465.76 | L5: 43492 | M5: 0.85625 | N5: Ewallet | O5: 8.4
A6: 373-73-7910 | B6: A | C6: Trichy | D6: Normal | E6: Male | F6: Sports and travel | G6: 86.31 | H6: 7 | I6: 30.2085 | J6: 634.3785 | K6: 604.17 | L6: 43679 | M6: 0.44236111 | N6: Ewallet | O6: 5.3
A7: 699-14-3026 | B7: C | C7: Chennai | D7: Normal | E7: Male | F7: Electronic accessories | G7: 85.39 | H7: 7 | I7: 29.8865 | J7: 627.6165 | K7: 597.73 | L7: 43549 | M7: 0.77083333 | N7: Ewallet | O7: 4.1
A8: 355-53-5943 | B8: A | C8: Trichy | D8: Member | E8: Female | F8: Electronic accessories | G8: 68.84 | H8: 6 | I8: 20.652 | J8: 433.692 | K8: 413.04 | L8: 43521 | M8: 0.60833333 | N8: Ewallet | O8: 5.8
A9: 315-22-5665 | B9: C | C9: Chennai | D9: Normal | E9: Female | F9: Home and lifestyle | G9: 73.56 | H9: 10 | I9: 36.78 | J9: 772.38 | K9: 735.6 | L9: 43520 | M9: 0.48472222 | N9: Ewallet | O9: 8
A10: 665-32-9167 | B10: A | C10: Trichy | D10: Member | E10: Female | F10: Health and beauty | G10: 36.26 | H10: 2 | I10: 3.626 | J10: 76.146 | K10: 72.52 | L10: 43739 | M10: 0.71875 | N10: Credit card | O10: 7.2
A11: 692-92-5582 | B11: B | C11: karur | D11: Member | E11: Female | F11: Food and beverages | G11: 54.84 | H11: 3 | I11: 8.226 | J11: 172.746 | K11: 164.52 | L11: 43516 | M11: 0.56041667 | N11: Credit card | O11: 5.9
A12: 351-62-0822 | B12: B | C12: karur | D12: Member | E12: Female | F12: Fashion accessories | G12: 14.48 | H12: 4 | I12: 2.896 | J12: 60.816 | K12: 57.92 | L12: 43618 | M12: 0.75486111 | N12: Ewallet | O12: 4.5
A13: 529-56-3974 | B13: B | C13: karur | D13: Member | E13: Male | F13: Electronic accessories | G13: 25.51 | H13: 4 | I13: 5.102 | J13: 107.142 | K13: 102.04 | L13: 43711 | M13: 0.71041667 | N13: Cash | O13: 6.8
A14: 365-64-0515 | B14: A | C14: Trichy | D14: Normal | E14: Female | F14: Electronic accessories | G14: 46.95 | H14: 5 | I14: 11.7375 | J14: 246.4875 | K14: 234.75 | L14: 43801 | M14: 0.43402778 | N14: Ewallet | O14: 7.1
A15: 252-56-2699 | B15: A | C15: Trichy | D15: Normal | E15: Male | F15: Food and beverages | G15: 43.19 | H15: 10 | I15: 21.595 | J15: 453.495 | K15: 431.9 | L15: 43648 | M15: 0.7 | N15: Ewallet | O15: 8.2
A16: 829-34-3910 | B16: A | C16: Trichy | D16: Normal | E16: Female | F16: Health and beauty | G16: 71.38 | H16: 10 | I16: 35.69 | J16: 749.49 | K16: 713.8 | L16: 43553 | M16: 0.80625 | N16: Cash | O16: 5.7
... A4034: 849-09-3907 | B4034: A | C4034: Trichy | D4034: Member | E4034: Female | F4034: Fashion accessories | G4034: 88.34 | H4034: 8 | I4034: 30.919 | J4034: 649.08865 | K4034: 618.38 | L4034: 45706 | M4034: 0.56111111 | N4034: Cash | O4034: 6.8659917

Sheet If_Functions
A1: Sl No | B1: Roll No | C1: Student Name | D1: Tamil / Language | E1: English | F1: Maths | G1: Science / Social | H1: Total / Sum | I1: Average / % | J1: Grade / Remarks | K1: AND =AND(I2=51.25,G2=52) | L1: OR =OR(I2=51.25,G2=51) | M1: NOT =NOT(N2) | N1: If function =IF(I2<55,"C","No Grade") | O1: If function =IF(I2<55,"C",IF(AND(I2>55,I2<70),"B","A")) | P1: IFERROR =IFERROR(I3/0,"cannot divide by zero") | Q1: IFNA =IFNA(P2,"no value")
A2: 7 | B2: 7 | C2: Manoj Reddy | D2: 50 | E2: 55 | F2: 48 | G2: 52 | H2: 205 | I2: 51.25 | J2: C | K2: =AND(I2=51.25,G2=52) -> TRUE | L2: =OR(I2=51.25,G2=51) -> TRUE | M2: =NOT(L2) -> FALSE | N2: =IF(I2<55,"C","No Grade") -> C | O2: =IF(I2<55,"C",IF(AND(I2>55,I2<70),"B","A")) -> C | P2: =IFERROR(I2/O2,"You cannot divide number by any letter") -> You cannot divide number by any letter | Q2: =_xlfn.IFNA(P2,"no value") -> You cannot divide number by any letter
A3: 11 | B3: 11 | C3: Deepak Sharma | D3: 45 | E3: 50 | F3: 42 | G3: 48 | H3: 185 | I3: 46.25 | J3: C | K3: =AND(I3=51.25,G3=52) -> FALSE | L3: =OR(I3=51.25,G3=51) -> FALSE | M3: =NOT(L3) -> TRUE | N3: =IF(I3<55,"C","No Grade") -> C | O3: =IF(I3<55,"C",IF(AND(I3>55,I3<70),"B","A")) -> C | P3: =IFERROR(I3/0,"cannot divide by zero") -> cannot divide by zero | Q3: =_xlfn.IFNA(P3,"no value") -> cannot divide by zero
A4: 3 | B4: 3 | C4: Rahul Verma | D4: 65 | E4: 70 | F4: 55 | G4: 60 | H4: 250 | I4: 62.5 | J4: B | K4: =AND(I4=51.25,G4=52) -> FALSE | L4: =OR(I4=51.25,G4=51) -> FALSE | M4: =NOT(L4) -> TRUE | N4: =IF(I4<55,"C","No Grade") -> No Grade | O4: =IF(I4<55,"C",IF(AND(I4>55,I4<70),"B","A")) -> B | P4: #N/A | Q4: =_xlfn.IFNA(P4,"no value") -> no value
A5: 5 | B5: 5 | C5: Vikram Patil | D5: 58 | E5: 63 | F5: 60 | G5: 55 | H5: 236 | I5: 59 | J5: B | K5: =AND(I5=51.25,G5=52) -> FALSE | L5: =OR(I5=51.25,G5=51) -> FALSE | M5: =NOT(L5) -> TRUE | N5: =IF(I5<55,"C","No Grade") -> No Grade | O5: =IF(I5<55,"C",IF(AND(I5>55,I5<70),"B","A")) -> B | Q5: =_xlfn.IFNA(P5,"no value") -> 0
A6: 9 | B6: 9 | C6: Sanjay Mehta | D6: 67 | E6: 70 | F6: 72 | G6: 65 | H6: 274 | I6: 68.5 | J6: B | K6: =AND(I6=51.25,G6=52) -> FALSE | L6: =OR(I6=51.25,G6=51) -> FALSE | M6: =NOT(L6) -> TRUE | N6: =IF(I6<55,"C","No Grade") -> No Grade | O6: =IF(I6<55,"C",IF(AND(I6>55,I6<70),"B","A")) -> B | Q6: =_xlfn.IFNA(P6,"no value") -> 0
A7: 13 | B7: 13 | C7: Arjun Singh | D7: 58 | E7: 62 | F7: 65 | G7: 60 | H7: 245 | I7: 61.25 | J7: B | K7: =AND(I7=51.25,G7=52) -> FALSE | L7: =OR(I7=51.25,G7=51) -> FALSE | M7: =NOT(L7) -> TRUE | N7: =IF(I7<55,"C","No Grade") -> No Grade | O7: =IF(I7<55,"C",IF(AND(I7>55,I7<70),"B","A")) -> B | Q7: =_xlfn.IFNA(P7,"no value") -> 0
A8: 15 | B8: 15 | C8: Suresh Kumar | D8: 70 | E8: 68 | F8: 72 | G8: 65 | H8: 275 | I8: 68.75 | J8: B | K8: =AND(I8=51.25,G8=52) -> FALSE | L8: =OR(I8=51.25,G8=51) -> FALSE | M8: =NOT(L8) -> TRUE | N8: =IF(I8<55,"C","No Grade") -> No Grade | O8: =IF(I8<55,"C",IF(AND(I8>55,I8<70),"B","A")) -> B | Q8: =_xlfn.IFNA(P8,"no value") -> 0
A9: 17 | B9: 17 | C9: Rohit Chopra | D9: 60 | E9: 58 | F9: 55 | G9: 62 | H9: 235 | I9: 58.75 | J9: B | K9: =AND(I9=51.25,G9=52) -> FALSE | L9: =OR(I9=51.25,G9=51) -> FALSE | M9: =NOT(L9) -> TRUE | N9: =IF(I9<55,"C","No Grade") -> No Grade | O9: =IF(I9<55,"C",IF(AND(I9>55,I9<70),"B","A")) -> B | Q9: =_xlfn.IFNA(P9,"no value") -> 0
A10: 19 | B10: 19 | C10: Karan Kapoor | D10: 66 | E10: 70 | F10: 68 | G10: 64 | H10: 268 | I10: 67 | J10: B | K10: =AND(I10=51.25,G10=52) -> FALSE | L10: =OR(I10=51.25,G10=51) -> FALSE | M10: =NOT(L10) -> TRUE | N10: =IF(I10<55,"C","No Grade") -> No Grade | O10: =IF(I10<55,"C",IF(AND(I10>55,I10<70),"B","A")) -> B | Q10: =_xlfn.IFNA(P10,"no value") -> 0
A11: 1 | B11: 1 | C11: Aakash Kumar | D11: 85 | E11: 78 | F11: 92 | G11: 88 | H11: 343 | I11: 85.75 | J11: A | K11: =AND(I11=51.25,G11=52) -> FALSE | L11: =OR(I11=51.25,G11=51) -> FALSE | M11: =NOT(L11) -> TRUE | N11: =IF(I11<55,"C","No Grade") -> No Grade | O11: =IF(I11<55,"C",IF(AND(I11>55,I11<70),"B","A")) -> A | Q11: =_xlfn.IFNA(P11,"no value") -> 0
A12: 2 | B12: 2 | C12: Priya Singh | D12: 74 | E12: 81 | F12: 69 | G12: 72 | H12: 296 | I12: 74 | J12: A | K12: =AND(I12=51.25,G12=52) -> FALSE | L12: =OR(I12=51.25,G12=51) -> FALSE | M12: =NOT(L12) -> TRUE | N12: =IF(I12<55,"C","No Grade") -> No Grade | O12: =IF(I12<55,"C",IF(AND(I12>55,I12<70),"B","A")) -> A | Q12: =_xlfn.IFNA(P12,"no value") -> 0
A13: 4 | B13: 4 | C13: Sneha Sharma | D13: 90 | E13: 88 | F13: 95 | G13: 93 | H13: 366 | I13: 91.5 | J13: A | K13: =AND(I13=51.25,G13=52) -> FALSE | L13: =OR(I13=51.25,G13=51) -> FALSE | M13: =NOT(L13) -> TRUE | N13: =IF(I13<55,"C","No Grade") -> No Grade | O13: =IF(I13<55,"C",IF(AND(I13>55,I13<70),"B","A")) -> A | Q13: =_xlfn.IFNA(P13,"no value") -> 0
A14: 6 | B14: 6 | C14: Anjali Gupta | D14: 72 | E14: 75 | F14: 80 | G14: 78 | H14: 305 | I14: 76.25 | J14: A | K14: =AND(I14=51.25,G14=52) -> FALSE | L14: =OR(I14=51.25,G14=51) -> FALSE | M14: =NOT(L14) -> TRUE | N14: =IF(I14<55,"C","No Grade") -> No Grade | O14: =IF(I14<55,"C",IF(AND(I14>55,I14<70),"B","A")) -> A | Q14: =_xlfn.IFNA(P14,"no value") -> 0
A15: 8 | B15: 8 | C15: Pooja Desai | D15: 88 | E15: 92 | F15: 90 | G15: 89 | H15: 359 | I15: 89.75 | J15: A | K15: =AND(I15=51.25,G15=52) -> FALSE | L15: =OR(I15=51.25,G15=51) -> FALSE | M15: =NOT(L15) -> TRUE | N15: =IF(I15<55,"C","No Grade") -> No Grade | O15: =IF(I15<55,"C",IF(AND(I15>55,I15<70),"B","A")) -> A | Q15: =_xlfn.IFNA(P15,"no value") -> 0
A16: 10 | B16: 10 | C16: Ritu Joshi | D16: 80 | E16: 78 | F16: 85 | G16: 82 | H16: 325 | I16: 81.25 | J16: A | K16: =AND(I16=51.25,G16=52) -> FALSE | L16: =OR(I16=51.25,G16=51) -> FALSE | M16: =NOT(L16) -> TRUE | N16: =IF(I16<55,"C","No Grade") -> No Grade | O16: =IF(I16<55,"C",IF(AND(I16>55,I16<70),"B","A")) -> A | Q16: =_xlfn.IFNA(P16,"no value") -> 0
... A21: 20 | B21: 20 | C21: Priyanka Singh | D21: 89 | E21: 92 | F21: 95 | G21: 90 | H21: 366 | I21: 91.5 | J21: A | K21: =AND(I21=51.25,G21=52) -> FALSE | L21: =OR(I21=51.25,G21=51) -> FALSE | M21: =NOT(L21) -> TRUE | N21: =IF(I21<55,"C","No Grade") -> No Grade | O21: =IF(I21<55,"C",IF(AND(I21>55,I21<70),"B","A")) -> A | Q21: =_xlfn.IFNA(P21,"no value") -> 0

Sheet Dataset
A1: Invoice ID | B1: Branch | C1: City | D1: Customer type | E1: Gender | F1: Product line | G1: Unit price | H1: Quantity | I1: Tax 5% | J1: Total | K1: cogs | L1: Date | M1: Time | N1: Payment | O1: Rating
A2: 750-67-8428 | B2: A | C2: Trichy | D2: Member | E2: Female | F2: Health and beauty | G2: 74.69 | H2: 7 | I2: 26.1415 | J2: 548.9715 | K2: 522.83 | L2: 43586 | M2: 0.54722222 | N2: Ewallet | O2: 9.1373232
A3: 226-31-3081 | B3: C | C3: Chennai | D3: Normal | E3: Female | F3: Electronic accessories | G3: 15.28 | H3: 5 | I3: 3.82 | J3: 80.22 | K3: 76.4 | L3: 43680 | M3: 0.43680556 | N3: Cash | O3: 9.6
A4: 631-41-3108 | B4: A | C4: Trichy | D4: Normal | E4: Male | F4: Home and lifestyle | G4: 46.33 | H4: 7 | I4: 16.2155 | J4: 340.5255 | K4: 324.31 | L4: 43527 | M4: 0.55763889 | N4: Credit card | O4: 7.4
A5: 123-19-1176 | B5: A | C5: Trichy | D5: Member | E5: Male | F5: Health and beauty | G5: 58.22 | H5: 8 | I5: 23.288 | J5: 489.048 | K5: 465.76 | L5: 43492 | M5: 0.85625 | N5: Ewallet | O5: 8.4
A6: 373-73-7910 | B6: A | C6: Trichy | D6: Normal | E6: Male | F6: Sports and travel | G6: 86.31 | H6: 7 | I6: 30.2085 | J6: 634.3785 | K6: 604.17 | L6: 43679 | M6: 0.44236111 | N6: Ewallet | O6: 5.3
A7: 699-14-3026 | B7: C | C7: Chennai | D7: Normal | E7: Male | F7: Electronic accessories | G7: 85.39 | H7: 7 | I7: 29.8865 | J7: 627.6165 | K7: 597.73 | L7: 43549 | M7: 0.77083333 | N7: Ewallet | O7: 4.1
A8: 355-53-5943 | B8: A | C8: Trichy | D8: Member | E8: Female | F8: Electronic accessories | G8: 68.84 | H8: 6 | I8: 20.652 | J8: 433.692 | K8: 413.04 | L8: 43521 | M8: 0.60833333 | N8: Ewallet | O8: 5.8
A9: 315-22-5665 | B9: C | C9: Chennai | D9: Normal | E9: Female | F9: Home and lifestyle | G9: 73.56 | H9: 10 | I9: 36.78 | J9: 772.38 | K9: 735.6 | L9: 43520 | M9: 0.48472222 | N9: Ewallet | O9: 8
A10: 665-32-9167 | B10: A | C10: Trichy | D10: Member | E10: Female | F10: Health and beauty | G10: 36.26 | H10: 2 | I10: 3.626 | J10: 76.146 | K10: 72.52 | L10: 43739 | M10: 0.71875 | N10: Credit card | O10: 7.2
A11: 692-92-5582 | B11: B | C11: karur | D11: Member | E11: Female | F11: Food and beverages | G11: 54.84 | H11: 3 | I11: 8.226 | J11: 172.746 | K11: 164.52 | L11: 43516 | M11: 0.56041667 | N11: Credit card | O11: 5.9
A12: 351-62-0822 | B12: B | C12: karur | D12: Member | E12: Female | F12: Fashion accessories | G12: 14.48 | H12: 4 | I12: 2.896 | J12: 60.816 | K12: 57.92 | L12: 43618 | M12: 0.75486111 | N12: Ewallet | O12: 4.5
A13: 529-56-3974 | B13: B | C13: karur | D13: Member | E13: Male | F13: Electronic accessories | G13: 25.51 | H13: 4 | I13: 5.102 | J13: 107.142 | K13: 102.04 | L13: 43711 | M13: 0.71041667 | N13: Cash | O13: 6.8
... A4034: 849-09-3907 | B4034: A | C4034: Trichy | D4034: Member | E4034: Female | F4034: Fashion accessories | G4034: 88.34 | H4034: 8 | I4034: 30.919 | J4034: 649.08865 | K4034: 618.38 | L4034: 45706 | M4034: 0.56111111 | N4034: Cash | O4034: 6.8659917

Sheet sumif
J1: Overall product total
A2: sno | B2: =Dataset!E1 -> Gender | C2: =Dataset!F1 -> Product line | D2: =Dataset!J1 -> Total | J2: Product line | K2: =SUMIF(C:C,J2,D:D)
A3: sno | B3: =Dataset!E2 -> Female | C3: =Dataset!F2 -> Health and beauty | D3: =Dataset!J2 -> 548.9715 | J3: Health and beauty | K3: =SUMIF(C:C,J3,D:D) -> 204470.84
A4: sno | B4: =Dataset!E3 -> Female | C4: =Dataset!F3 -> Electronic accessories | D4: =Dataset!J3 -> 80.22 | J4: Electronic accessories | K4: =SUMIF(C:C,J4,D:D) -> 225535.74
A5: sno | B5: =Dataset!E4 -> Male | C5: =Dataset!F4 -> Home and lifestyle | D5: =Dataset!J4 -> 340.5255 | J5: Home and lifestyle | K5: =SUMIF(C:C,J5,D:D) -> 224162.13
A6: sno | B6: =Dataset!E5 -> Male | C6: =Dataset!F5 -> Health and beauty | D6: =Dataset!J5 -> 489.048 | J6: Sports and travel | K6: =SUMIF(C:C,J6,D:D) -> 229706.14
A7: sno | B7: =Dataset!E6 -> Male | C7: =Dataset!F6 -> Sports and travel | D7: =Dataset!J6 -> 634.3785 | J7: Food and beverages | K7: =SUMIF(C:C,J7,D:D) -> 234200.77
A8: sno | B8: =Dataset!E7 -> Male | C8: =Dataset!F7 -> Electronic accessories | D8: =Dataset!J7 -> 627.6165 | J8: Fashion accessories | K8: =SUMIF(C:C,J8,D:D) -> 227797.08
A9: sno | B9: =Dataset!E8 -> Female | C9: =Dataset!F8 -> Electronic accessories | D9: =Dataset!J8 -> 433.692
A10: sno | B10: =Dataset!E9 -> Female | C10: =Dataset!F9 -> Home and lifestyle | D10: =Dataset!J9 -> 772.38
A11: sno | B11: =Dataset!E10 -> Female | C11: =Dataset!F10 -> Health and beauty | D11: =Dataset!J10 -> 76.146
A12: sno | B12: =Dataset!E11 -> Female | C12: =Dataset!F11 -> Food and beverages | D12: =Dataset!J11 -> 172.746
A13: sno | B13: =Dataset!E12 -> Female | C13: =Dataset!F12 -> Fashion accessories | D13: =Dataset!J12 -> 60.816
A14: sno | B14: =Dataset!E13 -> Male | C14: =Dataset!F13 -> Electronic accessories | D14: =Dataset!J13 -> 107.142
A15: sno | B15: =Dataset!E14 -> Female | C15: =Dataset!F14 -> Electronic accessories | D15: =Dataset!J14 -> 246.4875
A16: sno | B16: =Dataset!E15 -> Male | C16: =Dataset!F15 -> Food and beverages | D16: =Dataset!J15 -> 453.495
A17: sno | B17: =Dataset!E16 -> Female | C17: =Dataset!F16 -> Health and beauty | D17: =Dataset!J16 -> 749.49
A18: sno | B18: =Dataset!E17 -> Female | C18: =Dataset!F17 -> Sports and travel | D18: =Dataset!J17 -> 590.436
A19: sno | B19: =Dataset!E18 -> Female | C19: =Dataset!F18 -> Health and beauty | D19: =Dataset!J18 -> 506.6355
A20: sno | B20: =Dataset!E19 -> Male | C20: =Dataset!F19 -> Sports and travel | D20: =Dataset!J19 -> 457.443
... A4035: sno | B4035: =Dataset!E4034 -> Female | C4035: =Dataset!F4034 -> Fashion accessories | D4035: =Dataset!J4034 -> 649.08865

Sheet Sheet1
A1: Invoice ID | B1: Branch | C1: City | D1: Customer type | E1: Gender | F1: Product line | G1: Unit price | H1: Quantity | I1: Tax 5% | J1: Total | K1: cogs | L1: Date | M1: Time | N1: Payment | O1: Rating | P1: level | T1: Product line | U1: TOTAL | V1: AVERAGE
A2: 300-71-4605 | C2: Chennai | D2: Member | E2: Male | F2: Electronic accessories | G2: 86.04 | H2: 5 | I2: 21.51 | J2: 451.71 | K2: 430.2 | L2: 43521 | M2: 0.475 | N2: Ewallet | O2: 4.8 | P2: low | T2: Electronic accessories | U2: =SUMIF(F:F,T2,J:J) -> 146566.17 | V2: =AVERAGEIF(F:F,T2,J:J) -> 215.53848 | W2: =COUNTIF(F:F,T2) -> 680
A3: 120-06-4233 | B3: C | C3: Chennai | D3: Normal | E3: Male | F3: Electronic accessories | G3: 30.61 | H3: 6 | I3: 9.183 | J3: 0 | K3: 183.66 | L3: 43802 | M3: 0.85833333 | N3: Cash | O3: 9.3 | P3: low | T3: Fashion accessories | U3: =SUMIF(F:F,T3,J:J) -> 135279.44 | V3: =AVERAGEIF(F:F,T3,J:J) -> 189.99921 | W3: =COUNTIF(F:F,T3) -> 712
A4: 841-35-6630 | B4: C | C4: Chennai | D4: Normal | E4: Female | F4: Electronic accessories | G4: 75.91 | H4: 6 | I4: 50000 | J4: 0 | K4: 455.46 | L4: 43711 | M4: 0.76458333 | N4: Cash | O4: 8.7 | P4: low | T4: Food and beverages | U4: =SUMIF(F:F,T4,J:J) -> 133759.83 | V4: =AVERAGEIF(F:F,T4,J:J) -> 192.18367 | W4: =COUNTIF(F:F,T4) -> 696
A5: 871-39-9221 | B5: C | C5: Chennai | D5: Normal | E5: Female | F5: Electronic accessories | G5: 12.45 | H5: 6 | I5: 3.735 | J5: 0 | K5: 74.7 | L5: 43710 | M5: 0.54930556 | N5: Cash | O5: 4.1 | P5: low | T5: Health and beauty | U5: =SUMIF(F:F,T5,J:J) -> 134587.82 | V5: =AVERAGEIF(F:F,T5,J:J) -> 221.36155 | W5: =COUNTIF(F:F,T5) -> 608
A6: 733-33-4967 | B6: C | C6: Chennai | D6: Normal | E6: Male | F6: Electronic accessories | G6: 20.85 | H6: 8 | I6: 8.34 | J6: 0 | K6: 166.8 | L6: 43527 | M6: 0.80347222 | N6: Cash | O6: 6.3 | P6: low | T6: Home and lifestyle | U6: =SUMIF(F:F,T6,J:J) -> 165881.26 | V6: =AVERAGEIF(F:F,T6,J:J) -> 259.18948 | W6: =COUNTIF(F:F,T6) -> 640
A7: 672-51-8681 | B7: C | C7: Chennai | D7: Member | E7: Female | F7: Electronic accessories | G7: 66.65 | H7: 9 | I7: 29.9925 | J7: 0 | K7: 599.85 | L7: 43556 | M7: 0.76319444 | N7: Credit card | O7: 9.7 | P7: low | T7: Sports and travel | U7: =SUMIF(F:F,T7,J:J) -> 162607.6 | V7: =AVERAGEIF(F:F,T7,J:J) -> 244.89097 | W7: =COUNTIF(F:F,T7) -> 664
A8: 380-94-4661 | B8: C | C8: Chennai | D8: Member | E8: Male | F8: Electronic accessories | G8: 65.94 | H8: 4 | I8: 13.188 | J8: 0 | K8: 263.76 | L8: 43648 | M8: 0.54513889 | N8: Credit card | O8: 6.9 | P8: low
A9: 211-05-0490 | B9: C | C9: Chennai | D9: Member | E9: Female | F9: Electronic accessories | G9: 51.92 | H9: 5 | I9: 12.98 | J9: 0 | K9: 259.6 | L9: 43527 | M9: 0.57083333 | N9: Cash | O9: 7.5 | P9: low
A10: 233-34-0817 | B10: C | C10: Chennai | D10: Member | E10: Female | F10: Electronic accessories | G10: 98.84 | H10: 1 | I10: 4.942 | J10: 0 | K10: 98.84 | L10: 43511 | M10: 0.47291667 | N10: Cash | O10: 8.4 | P10: low
A11: 556-97-7101 | B11: C | C11: Chennai | D11: Normal | E11: Female | F11: Electronic accessories | G11: 63.22 | H11: 2 | I11: 6.322 | J11: 0 | K11: 126.44 | L11: 43466 | M11: 0.66041667 | N11: Cash | O11: 8.5 | P11: low
A12: 219-61-4139 | B12: C | C12: Chennai | D12: Normal | E12: Male | F12: Electronic accessories | G12: 83.08 | H12: 1 | I12: 4.154 | J12: 0 | K12: 83.08 | L12: 43488 | M12: 0.71944444 | N12: Ewallet | O12: 6.4 | P12: low
A13: 273-84-2164 | B13: C | C13: Chennai | D13: Member | E13: Male | F13: Electronic accessories | G13: 12.05 | H13: 5 | I13: 3.0125 | J13: 0 | K13: 60.25 | L13: 43512 | M13: 0.66180556 | N13: Ewallet | O13: 5.5 | P13: low | T13: Product line | U13: Female | V13: Male | W13: TOTAL
A14: 740-11-5257 | B14: C | C14: Chennai | D14: Normal | E14: Male | F14: Electronic accessories | G14: 24.74 | H14: 10 | I14: 12.37 | J14: 0 | K14: 247.4 | L14: 43520 | M14: 0.69722222 | N14: Cash | O14: 7.1 | P14: low | T14: Electronic accessories | U14: =SUMIFS(J:J,F:F,T14,E:E,U13) -> 74910.188 | V14: =SUMIFS(J:J,E:E,V13,F:F,T14) -> 71655.979 | W14: =SUMIF(F:F,T14,J:J) -> 146566.17
A15: 183-21-3799 | B15: C | C15: Chennai | D15: Normal | E15: Female | F15: Electronic accessories | G15: 77.63 | H15: 9 | I15: 34.9335 | J15: 0 | K15: 698.67 | L15: 43515 | M15: 0.63472222 | N15: Ewallet | O15: 7.2 | P15: low | T15: Fashion accessories | W15: =SUMIF(F:F,T15,J:J) -> 135279.44
A16: 377-79-7592 | B16: C | C16: Chennai | D16: Member | E16: Female | F16: Electronic accessories | G16: 44.84 | H16: 9 | I16: 20.178 | J16: 0 | K16: 403.56 | L16: 43479 | M16: 0.58333333 | N16: Credit card | O16: 7.5 | P16: low | T16: Food and beverages | W16: =SUMIF(F:F,T16,J:J) -> 133759.83
A17: 151-27-8496 | B17: C | C17: Chennai | D17: Normal | E17: Female | F17: Electronic accessories | G17: 56.13 | H17: 4 | I17: 11.226 | J17: 0 | K17: 224.52 | L17: 43484 | M17: 0.48819444 | N17: Ewallet | O17: 8.6 | P17: low | T17: Health and beauty | W17: =SUMIF(F:F,T17,J:J) -> 134587.82
A18: 717-96-4189 | B18: C | C18: Chennai | D18: Normal | E18: Female | F18: Electronic accessories | G18: 35.49 | H18: 6 | I18: 10.647 | J18: 0 | K18: 212.94 | L18: 43498 | M18: 0.52777778 | N18: Cash | O18: 4.1 | P18: low | T18: Home and lifestyle | W18: =SUMIF(F:F,T18,J:J) -> 165881.26
A19: 267-62-7380 | B19: C | C19: Chennai | D19: Member | E19: Male | F19: Electronic accessories | G19: 82.34 | H19: 10 | I19: 41.17 | J19: 0 | K19: 823.4 | L19: 43553 | M19: 0.8 | N19: Ewallet | O19: 4.3 | P19: low | T19: Sports and travel | W19: =SUMIF(F:F,T19,J:J) -> 162607.6
A20: 699-14-3026 | B20: C | C20: Chennai | D20: Normal | E20: Male | F20: Electronic accessories | G20: 85.39 | H20: 6 | I20: 29.8865 | J20: 0 | K20: 597.73 | L20: 44645 | M20: 0.77083333 | N20: Ewallet | O20: 3.9647259 | P20: low
A21: 871-39-9221 | B21: C | C21: Chennai | D21: Normal | E21: Female | F21: Electronic accessories | G21: 12.45 | H21: 5 | I21: 3.735 | J21: 0 | K21: 74.7 | L21: 44806 | M21: 0.54930556 | N21: Cash | O21: 3.9647259 | P21: low
A22: 733-33-4967 | B22: C | C22: Chennai | D22: Normal | E22: Male | F22: Electronic accessories | G22: 20.85 | H22: 7 | I22: 8.34 | J22: 0 | K22: 166.8 | L22: 44623 | M22: 0.80347222 | N22: Cash | O22: 6.0921397 | P22: low
A23: 211-05-0490 | B23: C | C23: Chennai | D23: Member | E23: Female | F23: Electronic accessories | G23: 51.92 | H23: 4 | I23: 12.98 | J23: 0 | K23: 259.6 | L23: 44623 | M23: 0.57083333 | N23: Cash | O23: 7.2525473 | P23: low
A24: 727-75-6477 | B24: C | C24: Chennai | D24: Normal | E24: Male | F24: Electronic accessories | G24: 28.84 | H24: 4 | I24: 5.768 | J24: 0 | K24: 115.36 | L24: 44649 | M24: 0.61388889 | N24: Cash | O24: 6.1888404 | P24: low
A25: 227-07-4446 | B25: C | C25: Chennai | D25: Member | E25: Female | F25: Electronic accessories | G25: 78.13 | H25: 9 | I25: 39.065 | J25: 0 | K25: 781.3 | L25: 44836 | M25: 0.86875 | N25: Cash | O25: 4.2548277 | P25: low
A26: 320-49-6392 | B26: C | C26: Chennai | D26: Normal | E26: Female | F26: Electronic accessories | G26: 30.24 | H26: 1 | I26: 1.512 | J26: 0 | K26: 30.24 | L26: 44654 | M26: 0.65555556 | N26: Cash | O26: 8.122853 | P26: low
A27: 122-61-9553 | B27: C | C27: Chennai | D27: Normal | E27: Female | F27: Electronic accessories | G27: 51.32 | H27: 8 | I27: 23.094 | J27: 0 | K27: 461.88 | L27: 44634 | M27: 0.81458333 | N27: Cash | O27: 5.4152353 | P27: low
A28: 598-47-9715 | B28: C | C28: Chennai | D28: Normal | E28: Male | F28: Electronic accessories | G28: 84.07 | H28: 4 | I28: 16.814 | J28: 0 | K28: 336.28 | L28: 44745 | M28: 0.70416667 | N28: Ewallet | O28: 4.2548277 | P28: low
A29: 399-69-4630 | B29: C | C29: Chennai | D29: Normal | E29: Male | F29: Electronic accessories | G29: 22.21 | H29: 5 | I29: 6.663 | J29: 0 | K29: 133.26 | L29: 44745 | M29: 0.43263889 | N29: Credit card | O29: 8.3162542 | P29: low
A30: 219-61-4139 | B30: C | C30: Chennai | D30: Normal | E30: Male | F30: Electronic accessories | G30: 83.08 | H30: 1 | I30: 4.154 | J30: 0 | K30: 83.08 | L30: 44584 | M30: 0.71944444 | N30: Ewallet | O30: 6.1888404 | P30: low
A31: 318-81-2368 | B31: C | C31: Chennai | D31: Normal | E31: Female | F31: Electronic accessories | G31: 46.2 | H31: 1 | I31: 2.31 | J31: 0 | K31: 46.2 | L31: 44639 | M31: 0.51111111 | N31: Cash | O31: 6.0921397 | P31: low
... A737: 433-08-7822 | B737: C | C737: Chennai | D737: Normal | E737: Female | F737: Health and beauty | G737: 78.89 | H737: 8 | I737: 27.6115 | J737: 0 | K737: 552.23 | L737: 45778 | M737: 0.825 | N737: Ewallet | O737: 7.8022633 | P737: mid
A738: 315-22-5665 | C738: Chennai | D738: Normal | E738: Female | F738: Home and lifestyle | G738: 73.56 | H738: 10 | I738: 36.78 | J738: 772.38 | K738: 735.6 | L738: 43520 | M738: 0.48472222 | N738: Ewallet | O738: 8 | P738: mid
A739: 565-80-5980 | B739: C | C739: Chennai | D739: Member | E739: Female | F739: Home and lifestyle | G739: 47.38 | H739: 4 | I739: 9.476 | J739: 0 | K739: 189.52 | L739: 43488 | M739: 0.43402778 | N739: Cash | O739: 7.1 | P739: mid
A740: 234-65-2137 | B740: C | C740: Chennai | D740: Normal | E740: Male | F740: Home and lifestyle | G740: 95.58 | H740: 10 | I740: 47.79 | J740: 0 | K740: 955.8 | L740: 43481 | M740: 0.56388889 | N740: Cash | O740: 4.8 | P740: mid
A741: 593-65-1552 | B741: C | C741: Chennai | D741: Normal | E741: Female | F741: Home and lifestyle | G741: 69.81 | H741: 4 | I741: 13.962 | J741: 0 | K741: 279.24 | L741: 43493 | M741: 0.86805556 | N741: Credit card | O741: 5.9 | P741: mid
A742: 523-38-0215 | B742: C | C742: Chennai | D742: Normal | E742: Male | F742: Home and lifestyle | G742: 37 | H742: 1 | I742: 1.85 | J742: 0 | K742: 37 | L742: 43619 | M742: 0.56180556 | N742: Credit card | O742: 7.9 | P742: mid
A743: 725-96-3778 | B743: C | C743: Chennai | D743: Member | E743: Female | F743: Home and lifestyle | G743: 89.25 | H743: 8 | I743: 35.7 | J743: 0 | K743: 714 | L743: 43485 | M743: 0.42569444 | N743: Cash | O743: 4.7 | P743: mid
A744: 651-61-0874 | B744: C | C744: Chennai | D744: Normal | E744: Male | F744: Home and lifestyle | G744: 46.22 | H744: 4 | I744: 9.244 | J744: 0 | K744: 184.88 | L744: 43802 | M744: 0.83611111 | N744: Credit card | O744: 6.2 | P744: mid
A745: 767-05-1286 | B745: C | C745: Chennai | D745: Member | E745: Female | F745: Home and lifestyle | G745: 83.77 | H745: 6 | I745: 25.131 | J745: 0 | K745: 502.62 | L745: 43488 | M745: 0.50694444 | N745: Ewallet | O745: 5.4 | P745: mid
A746: 556-72-8512 | B746: C | C746: Chennai | D746: Normal | E746: Male | F746: Home and lifestyle | G746: 22.96 | H746: 1 | I746: 1.148 | J746: 0 | K746: 22.96 | L746: 43495 | M746: 0.86597222 | N746: Cash | O746: 4.3 | P746: mid
A747: 620-02-2046 | B747: C | C747: Chennai | D747: Normal | E747: Male | F747: Home and lifestyle | G747: 69.4 | H747: 2 | I747: 6.94 | J747: 0 | K747: 138.8 | L747: 43492 | M747: 0.825 | N747: Ewallet | O747: 9 | P747: mid
A748: 602-80-9671 | B748: C | C748: Chennai | D748: Member | E748: Female | F748: Home and lifestyle | G748: 15.95 | H748: 6 | I748: 4.785 | J748: 0 | K748: 95.7 | L748: 43710 | M748: 0.71875 | N748: Credit card | O748: 5.1 | P748: mid
A749: 521-18-7827 | B749: C | C749: Chennai | D749: Member | E749: Male | F749: Home and lifestyle | G749: 39.39 | H749: 5 | I749: 9.8475 | J749: 0 | K749: 196.95 | L749: 43487 | M749: 0.86527778 | N749: Credit card | O749: 8.7 | P749: mid
A750: 386-27-7606 | B750: C | C750: Chennai | D750: Member | E750: Female | F750: Home and lifestyle | G750: 81.2 | H750: 7 | I750: 28.42 | J750: 0 | K750: 568.4 | L750: 43547 | M750: 0.66597222 | N750: Credit card | O750: 8.1 | P750: mid
... A1517: 727-46-3608 | B1517: B | C1517: karur | D1517: Member | E1517: Female | F1517: Food and beverages | G1517: 20.01 | H1517: 10 | I1517: 9.0045 | J1517: 199.53855 | K1517: 180.09 | L1517: 45445 | M1517: 0.65763889 | N1517: Ewallet | O1517: 4.4482084 | P1517: low
A1518: 727-46-3608 | C1518: karur | D1518: Member | E1518: Female | F1518: Food and beverages | G1518: 20.01 | H1518: 9 | I1518: 9.0045 | J1518: 189.0945 | K1518: 180.09 | L1518: 43618 | M1518: 0.65763889 | N1518: Ewallet | O1518: 4.1 | P1518: low
A1519: 727-46-3608 | B1519: B | C1519: karur | D1519: Member | E1519: Female | F1519: Food and beverages | G1519: 20.01 | H1519: 10 | I1519: 9.0045 | J1519: 189.03324 | K1519: 180.09 | L1519: 45810 | M1519: 0.65763889 | N1519: Ewallet | O1519: 4.2652373 | P1519: low
A1520: 135-13-8269 | B1520: B | C1520: karur | D1520: Member | E1520: Female | F1520: Food and beverages | G1520: 78.88 | H1520: 2 | I1520: 7.888 | J1520: 178.28504 | K1520: 157.76 | L1520: 44587 | M1520: 0.66944444 | N1520: Cash | O1520: 8.7997574 | P1520: low
A1521: 770-42-8960 | B1521: B | C1521: karur | D1521: Normal | E1521: Male | F1521: Food and beverages | G1521: 21.12 | H1521: 9 | I1521: 8.448 | J1521: 177.35053 | K1521: 168.96 | L1521: 45658 | M1521: 0.81319444 | N1521: Cash | O1521: 6.5539012 | P1521: low
A1522: 518-71-6847 | B1522: B | C1522: karur | D1522: Member | E1522: Male | F1522: Food and beverages | G1522: 26.6 | H1522: 6 | I1522: 7.98 | J1522: 176.83576 | K1522: 159.6 | L1522: 45348 | M1522: 0.63194444 | N1522: Ewallet | O1522: 5.3161515 | P1522: low
A1523: 518-71-6847 | B1523: B | C1523: karur | D1523: Member | E1523: Male | F1523: Food and beverages | G1523: 26.6 | H1523: 6 | I1523: 7.98 | J1523: 167.58 | K1523: 159.6 | L1523: 43522 | M1523: 0.63194444 | N1523: Ewallet | O1523: 4.9 | P1523: low
A1524: 414-12-7047 | B1524: B | C1524: karur | D1524: Normal | E1524: Male | F1524: Food and beverages | G1524: 19.79 | H1524: 8 | I1524: 7.916 | J1524: 166.236 | K1524: 158.32 | L1524: 43483 | M1524: 0.50277778 | N1524: Ewallet | O1524: 8.7 | P1524: low
A1525: 414-12-7047 | B1525: B | C1525: karur | D1525: Normal | E1525: Male | F1525: Food and beverages | G1525: 19.79 | H1525: 9 | I1525: 7.916 | J1525: 166.18215 | K1525: 158.32 | L1525: 45675 | M1525: 0.50277778 | N1525: Ewallet | O1525: 9.0506254 | P1525: low
A1526: 596-42-3999 | B1526: B | C1526: karur | D1526: Normal | E1526: Male | F1526: Food and beverages | G1526: 18.22 | H1526: 7 | I1526: 6.377 | J1526: 133.917 | K1526: 127.54 | L1526: 43741 | M1526: 0.58611111 | N1526: Credit card | O1526: 6.6 | P1526: low
A1527: 349-97-8902 | B1527: B | C1527: karur | D1527: Member | E1527: Male | F1527: Food and beverages | G1527: 57.89 | H1527: 2 | I1527: 5.789 | J1527: 130.84332 | K1527: 115.78 | L1527: 44578 | M1527: 0.44236111 | N1527: Ewallet | O1527: 8.6063561 | P1527: low
A1528: 349-97-8902 | B1528: B | C1528: karur | D1528: Member | E1528: Male | F1528: Food and beverages | G1528: 57.89 | H1528: 2 | I1528: 5.789 | J1528: 128.28348 | K1528: 115.78 | L1528: 45308 | M1528: 0.44236111 | N1528: Ewallet | O1528: 9.6558669 | P1528: low
A1529: 349-97-8902 | B1529: B | C1529: karur | D1529: Member | E1529: Male | F1529: Food and beverages | G1529: 57.89 | H1529: 2 | I1529: 5.789 | J1529: 121.52962 | K1529: 115.78 | L1529: 45674 | M1529: 0.44236111 | N1529: Ewallet | O1529: 9.2586858 | P1529: low
A1530: 434-35-9162 | B1530: B | C1530: karur | D1530: Member | E1530: Male | F1530: Food and beverages | G1530: 23.34 | H1530: 4 | I1530: 4.668 | J1530: 105.50641 | K1530: 93.36 | L1530: 44653 | M1530: 0.78680556 | N1530: Ewallet | O1530: 7.1558467 | P1530: low
... A1925: 686-41-0932 | B1925: B | C1925: karur | D1925: Normal | E1925: Female | F1925: Fashion accessories | G1925: 34.7 | H1925: 2 | I1925: 3.47 | J1925: 76.894747 | K1925: 69.4 | L1925: 45364 | M1925: 0.825 | N1925: Ewallet | O1925: 8.8964167 | P1925: mid
A1926: 616-24-2851 | C1926: karur | D1926: Member | E1926: Female | F1926: Fashion accessories | G1926: 17.87 | H1926: 4 | I1926: 3.574 | J1926: 75.054 | K1926: 71.48 | L1926: 43546 | M1926: 0.6125 | N1926: Ewallet | O1926: 6.5 | P1926: mid
A1927: 686-41-0932 | B1927: B | C1927: karur | D1927: Normal | E1927: Female | F1927: Fashion accessories | G1927: 34.7 | H1927: 2 | I1927: 3.47 | J1927: 72.87 | K1927: 69.4 | L1927: 43537 | M1927: 0.825 | N1927: Ewallet | O1927: 8.2 | P1927: mid
A1928: 351-62-0822 | B1928: B | C1928: karur | D1928: Member | E1928: Female | F1928: Fashion accessories | G1928: 14.48 | H1928: 4 | I1928: 2.896 | J1928: 65.455562 | K1928: 57.92 | L1928: 44714 | M1928: 0.75486111 | N1928: Ewallet | O1928: 4.3515284 | P1928: mid
A1929: 351-62-0822 | B1929: B | C1929: karur | D1929: Member | E1929: Female | F1929: Fashion accessories | G1929: 14.48 | H1929: 4 | I1929: 2.896 | J1929: 64.174982 | K1929: 57.92 | L1929: 45445 | M1929: 0.75486111 | N1929: Ewallet | O1929: 4.8821799 | P1929: mid
A1930: 676-10-2200 | B1930: B | C1930: karur | D1930: Member | E1930: Male | F1930: Fashion accessories | G1930: 53.78 | H1930: 1 | I1930: 2.689 | J1930: 60.776936 | K1930: 53.78 | L1930: 44622 | M1930: 0.84236111 | N1930: Ewallet | O1930: 4.5449296 | P1930: mid
A1931: 659-65-8956 | B1931: B | C1931: karur | D1931: Member | E1931: Male | F1931: Fashion accessories | G1931: 51.36 | H1931: 1 | I1931: 2.568 | J1931: 56.906545 | K1931: 51.36 | L1931: 45307 | M1931: 0.64305556 | N1931: Ewallet | O1931: 5.6416301 | P1931: mid
A1932: 837-55-7229 | B1932: B | C1932: karur | D1932: Normal | E1932: Female | F1932: Fashion accessories | G1932: 47.44 | H1932: 1 | I1932: 2.372 | J1932: 53.612084 | K1932: 47.44 | L1932: 44614 | M1932: 0.76319444 | N1932: Credit card | O1932: 6.5756429 | P1932: mid
A1933: 574-31-8277 | B1933: B | C1933: karur | D1933: Member | E1933: Male | F1933: Fashion accessories | G1933: 33.63 | H1933: 1 | I1933: 1.6815 | J1933: 37.261821 | K1933: 33.63 | L1933: 45371 | M1933: 0.82986111 | N1933: Cash | O1933: 6.0756017 | P1933: mid
A1934: 649-29-6775 | B1934: B | C1934: karur | D1934: Normal | E1934: Male | F1934: Fashion accessories | G1934: 33.52 | H1934: 1 | I1934: 1.676 | J1934: 37.139941 | K1934: 33.52 | L1934: 45506 | M1934: 0.64652778 | N1934: Cash | O1934: 7.2690234 | P1934: mid
A1935: 574-31-8277 | B1935: B | C1935: karur | D1935: Member | E1935: Male | F1935: Fashion accessories | G1935: 33.63 | H1935: 1 | I1935: 1.6815 | J1935: 35.300061 | K1935: 33.63 | L1935: 45736 | M1935: 0.82986111 | N1935: Cash | O1935: 5.8256899 | P1935: mid
A1936: 746-04-1077 | B1936: B | C1936: karur | D1936: Member | E1936: Female | F1936: Food and beverages | G1936: 84.63 | H1936: 10 | I1936: 42.315 | J1936: 888.615 | K1936: 846.3 | L1936: 43466 | M1936: 0.48333333 | N1936: Credit card | O1936: 9 | P1936: mid
A1937: 746-04-1077 | B1937: B | C1937: karur | D1937: Member | E1937: Female | F1937: Food and beverages | G1937: 84.63 | H1937: 11 | I1937: 42.315 | J1937: 888.32713 | K1937: 846.3 | L1937: 45658 | M1937: 0.48333333 | N1937: Credit card | O1937: 9.3627159 | P1937: mid
A1938: 234-03-4040 | B1938: B | C1938: karur | D1938: Member | E1938: Female | F1938: Food and beverages | G1938: 73.05 | H1938: 9 | I1938: 36.525 | J1938: 825.5402 | K1938: 730.5 | L1938: 44623 | M1938: 0.51736111 | N1938: Credit card | O1938: 8.4129549 | P1938: mid
... A3152: 531-80-1784 | B3152: A | C3152: Trichy | D3152: Normal | E3152: Male | F3152: Electronic accessories | G3152: 26.02 | H3152: 8 | I3152: 9.107 | J3152: 191.18504 | K3152: 182.14 | L3152: 45744 | M3152: 0.73472222 | N3152: Cash | O3152: 5.305539 | P3152: mid
A3153: 636-48-8204 | C3153: Trichy | D3153: Normal | E3153: Male | F3153: Electronic accessories | G3153: 34.56 | H3153: 5 | I3153: 8.64 | J3153: 181.44 | K3153: 172.8 | L3153: 43513 | M3153: 0.46875 | N3153: Ewallet | O3153: 9.9 | P3153: mid
A3154: 831-07-6050 | B3154: A | C3154: Trichy | D3154: Normal | E3154: Male | F3154: Electronic accessories | G3154: 32.71 | H3154: 5 | I3154: 8.1775 | J3154: 171.7275 | K3154: 163.55 | L3154: 43543 | M3154: 0.47916667 | N3154: Credit card | O3154: 9.9 | P3154: mid
A3155: 459-50-7686 | B3155: A | C3155: Trichy | D3155: Normal | E3155: Female | F3155: Electronic accessories | G3155: 23.46 | H3155: 5 | I3155: 7.038 | J3155: 159.07329 | K3155: 140.76 | L3155: 44574 | M3155: 0.80138889 | N3155: Ewallet | O3155: 6.1888404 | P3155: mid
A3156: 340-66-0321 | B3156: A | C3156: Trichy | D3156: Member | E3156: Male | F3156: Electronic accessories | G3156: 36.36 | H3156: 4 | I3156: 7.272 | J3156: 152.66253 | K3156: 145.44 | L3156: 45741 | M3156: 0.54652778 | N3156: Cash | O3156: 7.9062935 | P3156: mid
A3157: 527-09-6272 | B3157: A | C3157: Trichy | D3157: Member | E3157: Female | F3157: Electronic accessories | G3157: 28.45 | H3157: 5 | I3157: 7.1125 | J3157: 149.3625 | K3157: 142.25 | L3157: 43545 | M3157: 0.42847222 | N3157: Credit card | O3157: 9.1 | P3157: mid
A3158: 700-81-1757 | B3158: A | C3158: Trichy | D3158: Normal | E3158: Female | F3158: Electronic accessories | G3158: 26.31 | H3158: 4 | I3158: 6.5775 | J3158: 148.66504 | K3158: 131.55 | L3158: 44579 | M3158: 0.87430556 | N3158: Credit card | O3158: 8.5096555 | P3158: mid
A3159: 459-50-7686 | B3159: A | C3159: Trichy | D3159: Normal | E3159: Female | F3159: Electronic accessories | G3159: 23.46 | H3159: 6 | I3159: 7.038 | J3159: 147.798 | K3159: 140.76 | L3159: 43478 | M3159: 0.80138889 | N3159: Ewallet | O3159: 6.4 | P3159: mid
A3160: 459-50-7686 | B3160: A | C3160: Trichy | D3160: Normal | E3160: Female | F3160: Electronic accessories | G3160: 23.46 | H3160: 6 | I3160: 7.038 | J3160: 147.75012 | K3160: 140.76 | L3160: 45670 | M3160: 0.80138889 | N3160: Ewallet | O3160: 6.6579313 | P3160: mid
A3161: 700-81-1757 | B3161: A | C3161: Trichy | D3161: Normal | E3161: Female | F3161: Electronic accessories | G3161: 26.31 | H3161: 5 | I3161: 6.5775 | J3161: 138.08275 | K3161: 131.55 | L3161: 45675 | M3161: 0.87430556 | N3161: Credit card | O3161: 9.1546556 | P3161: mid
A3162: 151-16-1484 | B3162: A | C3162: Trichy | D3162: Member | E3162: Male | F3162: Electronic accessories | G3162: 32.25 | H3162: 4 | I3162: 6.45 | J3162: 135.40612 | K3162: 129 | L3162: 45701 | M3162: 0.52638889 | N3162: Ewallet | O3162: 6.7619615 | P3162: mid
A3163: 594-34-4444 | B3163: A | C3163: Trichy | D3163: Normal | E3163: Male | F3163: Electronic accessories | G3163: 97.16 | H3163: 1 | I3163: 4.858 | J3163: 107.65265 | K3163: 97.16 | L3163: 45507 | M3163: 0.85972222 | N3163: Ewallet | O3163: 7.8114879 | P3163: mid
A3164: 702-72-0487 | B3164: A | C3164: Trichy | D3164: Normal | E3164: Female | F3164: Electronic accessories | G3164: 46.61 | H3164: 2 | I3164: 4.661 | J3164: 105.3482 | K3164: 93.22 | L3164: 44618 | M3164: 0.51944444 | N3164: Credit card | O3164: 6.3822416 | P3164: mid
A3165: 674-56-6360 | B3165: A | C3165: Trichy | D3165: Normal | E3165: Male | F3165: Electronic accessories | G3165: 95.15 | H3165: 1 | I3165: 4.7575 | J3165: 99.875134 | K3165: 95.15 | L3165: 45738 | M3165: 0.58333333 | N3165: Cash | O3165: 6.2418106 | P3165: mid
... A3209: 381-20-0914 | B3209: A | C3209: Trichy | D3209: Member | E3209: Female | F3209: Fashion accessories | G3209: 20.01 | H3209: 10 | I3209: 9.0045 | J3209: 189.03324 | K3209: 180.09 | L3209: 45992 | M3209: 0.65833333 | N3209: Credit card | O3209: 5.9297201 | P3209: mid
A3210: 189-17-4241 | C3210: Trichy | D3210: Normal | E3210: Female | F3210: Fashion accessories | G3210: 87.67 | H3210: 2 | I3210: 8.767 | J3210: 184.107 | K3210: 175.34 | L3210: 43741 | M3210: 0.51180556 | N3210: Credit card | O3210: 7.7 | P3210: mid
A3211: 848-42-2560 | B3211: A | C3211: Trichy | D3211: Normal | E3211: Female | F3211: Fashion accessories | G3211: 81.91 | H3211: 2 | I3211: 8.191 | J3211: 181.51149 | K3211: 163.82 | L3211: 45415 | M3211: 0.73819444 | N3211: Cash | O3211: 8.4624452 | P3211: mid
A3212: 497-36-0989 | B3212: A | C3212: Trichy | D3212: Normal | E3212: Male | F3212: Fashion accessories | G3212: 51.94 | H3212: 3 | I3212: 7.791 | J3212: 172.64754 | K3212: 155.82 | L3212: 45337 | M3212: 0.63958333 | N3212: Cash | O3212: 8.5709381 | P3212: mid
A3213: 795-49-7276 | B3213: A | C3213: Trichy | D3213: Normal | E3213: Male | F3213: Fashion accessories | G3213: 37.15 | H3213: 4 | I3213: 7.43 | J3213: 155.97945 | K3213: 148.6 | L3213: 45739 | M3213: 0.79097222 | N3213: Ewallet | O3213: 8.6345047 | P3213: mid
A3214: 788-21-5741 | B3214: A | C3214: Trichy | D3214: Normal | E3214: Male | F3214: Fashion accessories | G3214: 45.38 | H3214: 3 | I3214: 6.807 | J3214: 150.84223 | K3214: 136.14 | L3214: 45339 | M3214: 0.56527778 | N3214: Credit card | O3214: 7.8114879 | P3214: mid
A3215: 760-53-9233 | B3215: A | C3215: Trichy | D3215: Member | E3215: Male | F3215: Fashion accessories | G3215: 41.28 | H3215: 3 | I3215: 6.192 | J3215: 139.95195 | K3215: 123.84 | L3215: 44646 | M3215: 0.77569444 | N3215: Credit card | O3215: 8.2195536 | P3215: mid
A3216: 760-53-9233 | B3216: A | C3216: Trichy | D3216: Member | E3216: Male | F3216: Fashion accessories | G3216: 41.28 | H3216: 3 | I3216: 6.192 | J3216: 137.21391 | K3216: 123.84 | L3216: 45377 | M3216: 0.77569444 | N3216: Credit card | O3216: 9.2218954 | P3216: mid
A3217: 760-53-9233 | B3217: A | C3217: Trichy | D3217: Member | E3217: Male | F3217: Fashion accessories | G3217: 41.28 | H3217: 3 | I3217: 6.192 | J3217: 129.98987 | K3217: 123.84 | L3217: 45742 | M3217: 0.77569444 | N3217: Credit card | O3217: 8.842565 | P3217: mid
A3218: 478-06-7835 | B3218: A | C3218: Trichy | D3218: Normal | E3218: Male | F3218: Fashion accessories | G3218: 89.69 | H3218: 1 | I3218: 4.4845 | J3218: 101.35893 | K3218: 89.69 | L3218: 44866 | M3218: 0.47222222 | N3218: Ewallet | O3218: 4.7383309 | P3218: mid
A3219: 247-11-2470 | B3219: A | C3219: Trichy | D3219: Member | E3219: Female | F3219: Fashion accessories | G3219: 22.32 | H3219: 4 | I3219: 4.464 | J3219: 100.89559 | K3219: 89.28 | L3219: 44564 | M3219: 0.68263889 | N3219: Credit card | O3219: 4.2548277 | P3219: mid
A3220: 478-06-7835 | B3220: A | C3220: Trichy | D3220: Normal | E3220: Male | F3220: Fashion accessories | G3220: 89.69 | H3220: 1 | I3220: 4.4845 | J3220: 99.375935 | K3220: 89.69 | L3220: 45597 | M3220: 0.47222222 | N3220: Ewallet | O3220: 5.3161515 | P3220: mid
A3221: 247-11-2470 | B3221: A | C3221: Trichy | D3221: Member | E3221: Female | F3221: Fashion accessories | G3221: 22.32 | H3221: 4 | I3221: 4.464 | J3221: 98.921658 | K3221: 89.28 | L3221: 45294 | M3221: 0.68263889 | N3221: Credit card | O3221: 4.773687 | P3221: mid
...
